README.txt
setup.cfg
setup.py
currency/__init__.py
currency.converter.egg-info/PKG-INFO
currency.converter.egg-info/SOURCES.txt
currency.converter.egg-info/dependency_links.txt
currency.converter.egg-info/entry_points.txt
currency.converter.egg-info/namespace_packages.txt
currency.converter.egg-info/not-zip-safe
currency.converter.egg-info/requires.txt
currency.converter.egg-info/top_level.txt
currency/converter/__init__.py
currency/converter/configure.zcml
currency/converter/currencies.py
currency/converter/currency_data.py
currency/converter/interfaces.py
currency/converter/setuphandlers.py
currency/converter/version.txt
currency/converter/browser/__init__.py
currency/converter/browser/configure.zcml
currency/converter/browser/currency_converter.py
currency/converter/browser/currency_converter_viewlet.py
currency/converter/browser/currency_manager.py
currency/converter/browser/viewlet_manager.py
currency/converter/browser/images/right_arrow.png
currency/converter/browser/templates/currency_converter.pt
currency/converter/browser/templates/currency_converter_viewlet.pt
currency/converter/browser/templates/currency_manager.pt
currency/converter/locales/currency.converter.pot
currency/converter/locales/en/LC_MESSAGES/currency.converter.po
currency/converter/locales/ja/LC_MESSAGES/currency.converter.po
currency/converter/portlets/__init__.py
currency/converter/portlets/configure.zcml
currency/converter/portlets/currency_converter.pt
currency/converter/portlets/currency_converter.py
currency/converter/profiles/default/componentregistry.xml
currency/converter/profiles/default/controlpanel.xml
currency/converter/profiles/default/metadata.xml
currency/converter/profiles/default/portlets.xml
currency/converter/profiles/default/propertiestool.xml
currency/converter/profiles/uninstall/componentregistry.xml
currency/converter/profiles/uninstall/currency.converter_uninstall.txt
currency/converter/tests/__init__.py
currency/converter/tests/base.py
currency/converter/tests/functional.txt
currency/converter/tests/integration.txt
currency/converter/tests/sample-90d.xml
currency/converter/tests/test_doctest.py
currency/converter/tests/test_portlet_currency_converter.py
currency/converter/tests/test_setup.py
currency/converter/tests/unittest.txt
currency/converter/utility/__init__.py
