Metadata-Version: 1.0
Name: currency.converter
Version: 0.5.2
Summary: Currency Converter
Home-page: http://pypi.python.org/pypi/currency.converter
Author: Taito Horiuchi
Author-email: taito.horiuchi@abita.fi
License: GPL
Platform: UNKNOWN
Classifier: Framework :: Plone
Classifier: Framework :: Zope2
Classifier: Framework :: Zope3
Classifier: Programming Language :: Python
Classifier: Topic :: Software Development :: Libraries :: Python Modules
